README.md
setup.py
gossh_python/__init__.py
gossh_python/common.py
gossh_python/rpc_session.py
gossh_python.egg-info/PKG-INFO
gossh_python.egg-info/SOURCES.txt
gossh_python.egg-info/dependency_links.txt
gossh_python.egg-info/not-zip-safe
gossh_python.egg-info/top_level.txt
gossh_python/built/__init__.py
gossh_python/built/build.py
gossh_python/built/go.py
gossh_python/built/gossh_python_go.py