Metadata-Version: 2.1
Name: gossh-python
Version: 1.0.0
Summary: gossh-python
Home-page: https://github.com/ftpsolutions/gossh-python
Author: Edward @ FTP Technologies
Author-email: edward.beech@ftpsolutions.com.au
License: MIT
Platform: UNKNOWN
Classifier: Development Status :: 3 - Alpha
Classifier: Intended Audience :: Developers
Classifier: Programming Language :: Python :: 3 :: Only
Classifier: Operating System :: POSIX
Classifier: Operating System :: Unix
Classifier: Operating System :: MacOS
